README.md
setup.py
HandyHTTP.egg-info/PKG-INFO
HandyHTTP.egg-info/SOURCES.txt
HandyHTTP.egg-info/dependency_links.txt
HandyHTTP.egg-info/not-zip-safe
HandyHTTP.egg-info/requires.txt
HandyHTTP.egg-info/top_level.txt
handyhttp/__init__.py
handyhttp/exceptions.py
handyhttp/responses.py
test/__init__.py
test/test_exceptions.py
test/test_responses.py