Metadata-Version: 2.1
Name: HandyHTTP
Version: 0.1.1
Summary: Helpers package for Python web projects.
Home-page: https://github.com/kmjbyrne/handyhttp
Author: Keith Byrne
Author-email: keithmbyrne@gmail.com
License: MIT
Keywords: python library utilities
Platform: UNKNOWN
Classifier: Development Status :: 3 - Alpha
Classifier: License :: OSI Approved :: MIT License
Classifier: Programming Language :: Python :: 3.7
